{
  "questions": [
    {
      "id": "M.7.32.S.1",
      "type": "MCQuestion",
      "text": "The present worth of ` 2310 due 1 2 years hence, the rate of interest being 15% per annum, is",
      "is_latex": false,
      "is_image": false,
      "image_url": null,
      "latex_string": null,
      "xp": 1,
      "tag": "",
      "difficulty": "EASY",
      "topic": "Financial Mathematics",
      "chapter": "True Discount",
      "option_list": [
        {
          "is_image": false,
          "is_latex": false,
          "text": "` 1750",
          "latex_string": null,
          "image_url": null,
          "is_correct": false
        },
        {
          "is_image": false,
          "is_latex": false,
          "text": "` 1680",
          "latex_string": null,
          "image_url": null,
          "is_correct": true
        },
        {
          "is_image": false,
          "is_latex": false,
          "text": "` 1840",
          "latex_string": null,
          "image_url": null,
          "is_correct": false
        },
        {
          "is_image": false,
          "is_latex": false,
          "text": "` 1443.75",
          "latex_string": null,
          "image_url": null,
          "is_correct": false
        }
      ]
    },
    {
      "id": "M.7.32.S.2",
      "type": "MCQuestion",
      "text": "If the true discount on a sum due 2 years hence at 14% per annum be ` 168, the sum due is",
      "is_latex": false,
      "is_image": false,
      "image_url": null,
      "latex_string": null,
      "xp": 1,
      "tag": "",
      "difficulty": "EASY",
      "topic": "Financial Mathematics",
      "chapter": "True Discount",
      "option_list": [
        {
          "is_image": false,
          "is_latex": false,
          "text": "` 768",
          "latex_string": null,
          "image_url": null,
          "is_correct": true
        },
        {
          "is_image": false,
          "is_latex": false,
          "text": "` 968",
          "latex_string": null,
          "image_url": null,
          "is_correct": false
        },
        {
          "is_image": false,
          "is_latex": false,
          "text": "` 1960",
          "latex_string": null,
          "image_url": null,
          "is_correct": false
        },
        {
          "is_image": false,
          "is_latex": false,
          "text": "` 2400",
          "latex_string": null,
          "image_url": null,
          "is_correct": false
        }
      ]
    },
    {
      "id": "M.7.32.S.3",
      "type": "MCQuestion",
      "text": "The true discount on ` 2562 due 4 months hence is ` 122. The rate percent is",
      "is_latex": false,
      "is_image": false,
      "image_url": null,
      "latex_string": null,
      "xp": 1,
      "tag": "",
      "difficulty": "EASY",
      "topic": "Financial Mathematics",
      "chapter": "True Discount",
      "option_list": [
        {
          "is_image": false,
          "is_latex": false,
          "text": "12%",
          "latex_string": null,
          "image_url": null,
          "is_correct": false
        },
        {
          "is_image": false,
          "is_latex": false,
          "text": "13%",
          "latex_string": null,
          "image_url": null,
          "is_correct": true
        },
        {
          "is_image": false,
          "is_latex": false,
          "text": "15%",
          "latex_string": null,
          "image_url": null,
          "is_correct": false
        },
        {
          "is_image": false,
          "is_latex": false,
          "text": "14%",
          "latex_string": null,
          "image_url": null,
          "is_correct": false
        }
      ]
    },
    {
      "id": "M.7.32.S.4",
      "type": "MCQuestion",
      "text": "The true discount on ` 1760 due after a certain time at 12% per annum is ` 160. The time after which it is due is",
      "is_latex": false,
      "is_image": false,
      "image_url": null,
      "latex_string": null,
      "xp": 1,
      "tag": "",
      "difficulty": "EASY",
      "topic": "Financial Mathematics",
      "chapter": "True Discount",
      "option_list": [
        {
          "is_image": false,
          "is_latex": false,
          "text": "6 months",
          "latex_string": null,
          "image_url": null,
          "is_correct": false
        },
        {
          "is_image": false,
          "is_latex": false,
          "text": "8 months",
          "latex_string": null,
          "image_url": null,
          "is_correct": false
        },
        {
          "is_image": false,
          "is_latex": false,
          "text": "9 months",
          "latex_string": null,
          "image_url": null,
          "is_correct": true
        },
        {
          "is_image": false,
          "is_latex": false,
          "text": "10 months",
          "latex_string": null,
          "image_url": null,
          "is_correct": false
        }
      ]
    },
    {
      "id": "M.7.32.S.5",
      "type": "MCQuestion",
      "text": "The true discount on a bill due 9 months hence at 16% per annum is ` 189. The amount of the bill is",
      "is_latex": false,
      "is_image": false,
      "image_url": null,
      "latex_string": null,
      "xp": 1,
      "tag": "",
      "difficulty": "EASY",
      "topic": "Financial Mathematics",
      "chapter": "True Discount",
      "option_list": [
        {
          "is_image": false,
          "is_latex": false,
          "text": "` 1386",
          "latex_string": null,
          "image_url": null,
          "is_correct": true
        },
        {
          "is_image": false,
          "is_latex": false,
          "text": "` 1764",
          "latex_string": null,
          "image_url": null,
          "is_correct": false
        },
        {
          "is_image": false,
          "is_latex": false,
          "text": "` 1575",
          "latex_string": null,
          "image_url": null,
          "is_correct": false
        },
        {
          "is_image": false,
          "is_latex": false,
          "text": "` 2268",
          "latex_string": null,
          "image_url": null,
          "is_correct": false
        }
      ]
    },
    {
      "id": "M.7.32.S.6",
      "type": "MCQuestion",
      "text": "The interest on ` 750 for 2 years is the same as the true discount on ` 960 due 2 years hence. If the rate of interest is the same in both cases, it is",
      "is_latex": false,
      "is_image": false,
      "image_url": null,
      "latex_string": null,
      "xp": 1,
      "tag": "",
      "difficulty": "EASY",
      "topic": "Financial Mathematics",
      "chapter": "True Discount",
      "option_list": [
        {
          "is_image": false,
          "is_latex": false,
          "text": "12%",
          "latex_string": null,
          "image_url": null,
          "is_correct": true
        },
        {
          "is_image": false,
          "is_latex": false,
          "text": "14%",
          "latex_string": null,
          "image_url": null,
          "is_correct": false
        },
        {
          "is_image": false,
          "is_latex": false,
          "text": "15%",
          "latex_string": null,
          "image_url": null,
          "is_correct": false
        },
        {
          "is_image": false,
          "is_latex": false,
          "text": "16%",
          "latex_string": null,
          "image_url": null,
          "is_correct": false
        }
      ]
    },
    {
      "id": "M.7.32.S.7",
      "type": "MCQuestion",
      "text": "The simple interest and the true discount on a certain sum for a given time and at a given rate are ` 85 and ` 80 respectively. The sum is",
      "is_latex": false,
      "is_image": false,
      "image_url": null,
      "latex_string": null,
      "xp": 1,
      "tag": "",
      "difficulty": "EASY",
      "topic": "Financial Mathematics",
      "chapter": "True Discount",
      "option_list": [
        {
          "is_image": false,
          "is_latex": false,
          "text": "` 1800",
          "latex_string": null,
          "image_url": null,
          "is_correct": false
        },
        {
          "is_image": false,
          "is_latex": false,
          "text": "` 1450",
          "latex_string": null,
          "image_url": null,
          "is_correct": true
        },
        {
          "is_image": false,
          "is_latex": false,
          "text": "` 1360",
          "latex_string": null,
          "image_url": null,
          "is_correct": false
        },
        {
          "is_image": false,
          "is_latex": false,
          "text": "` 6800",
          "latex_string": null,
          "image_url": null,
          "is_correct": false
        }
      ]
    },
    {
      "id": "M.7.32.S.8",
      "type": "MCQuestion",
      "text": "If ` 10 be allowed as true discount on a bill of ` 110 due at the end of a certain time, then the discount allowed on the same sum due at the end of double the time is",
      "is_latex": false,
      "is_image": false,
      "image_url": null,
      "latex_string": null,
      "xp": 1,
      "tag": "",
      "difficulty": "EASY",
      "topic": "Financial Mathematics",
      "chapter": "True Discount",
      "option_list": [
        {
          "is_image": false,
          "is_latex": false,
          "text": "` 20",
          "latex_string": null,
          "image_url": null,
          "is_correct": false
        },
        {
          "is_image": false,
          "is_latex": false,
          "text": "` 21.81",
          "latex_string": null,
          "image_url": null,
          "is_correct": false
        },
        {
          "is_image": false,
          "is_latex": false,
          "text": "` 22",
          "latex_string": null,
          "image_url": null,
          "is_correct": false
        },
        {
          "is_image": false,
          "is_latex": false,
          "text": "` 18.33",
          "latex_string": null,
          "image_url": null,
          "is_correct": true
        }
      ]
    },
    {
      "id": "M.7.32.S.9",
      "type": "MCQuestion",
      "text": "A man wants to sell his scooter. There are two offers, one at ` 12,000 cash and the other at a credit of ` 12,880 to be paid after 8 months, money being at 18% per annum. Which is the better offer?",
      "is_latex": false,
      "is_image": false,
      "image_url": null,
      "latex_string": null,
      "xp": 1,
      "tag": "",
      "difficulty": "EASY",
      "topic": "Financial Mathematics",
      "chapter": "True Discount",
      "option_list": [
        {
          "is_image": false,
          "is_latex": false,
          "text": "` 12,000 in cash",
          "latex_string": null,
          "image_url": null,
          "is_correct": true
        },
        {
          "is_image": false,
          "is_latex": false,
          "text": "` 12,880 at credit",
          "latex_string": null,
          "image_url": null,
          "is_correct": false
        },
        {
          "is_image": false,
          "is_latex": false,
          "text": "Both are equally good",
          "latex_string": null,
          "image_url": null,
          "is_correct": false
        },
        {
          "is_image": false,
          "is_latex": false,
          "text": "None of the Above",
          "latex_string": null,
          "image_url": null,
          "is_correct": false
        }
      ]
    },
    {
      "id": "M.7.32.S.10",
      "type": "MCQuestion",
      "text": "Goods were bought for ` 600 and sold the same day for ` 688.50 at a credit of 9 months and thus gaining 2%. The rate of interest per annum is",
      "is_latex": false,
      "is_image": false,
      "image_url": null,
      "latex_string": null,
      "xp": 1,
      "tag": "",
      "difficulty": "EASY",
      "topic": "Financial Mathematics",
      "chapter": "True Discount",
      "option_list": [
        {
          "is_image": false,
          "is_latex": false,
          "text": "2 16%",
          "latex_string": null,
          "image_url": null,
          "is_correct": true
        },
        {
          "is_image": false,
          "is_latex": false,
          "text": "1 14%",
          "latex_string": null,
          "image_url": null,
          "is_correct": false
        },
        {
          "is_image": false,
          "is_latex": false,
          "text": "1 13%",
          "latex_string": null,
          "image_url": null,
          "is_correct": false
        },
        {
          "is_image": false,
          "is_latex": false,
          "text": "15%",
          "latex_string": null,
          "image_url": null,
          "is_correct": false
        }
      ]
    },
    {
      "id": "M.7.32.S.11",
      "type": "MCQuestion",
      "text": "The present worth of ` 1404 due in two equal half-yearly instalments at 8% per annum simple interest is",
      "is_latex": false,
      "is_image": false,
      "image_url": null,
      "latex_string": null,
      "xp": 1,
      "tag": "",
      "difficulty": "EASY",
      "topic": "Financial Mathematics",
      "chapter": "True Discount",
      "option_list": [
        {
          "is_image": false,
          "is_latex": false,
          "text": "` 1325",
          "latex_string": null,
          "image_url": null,
          "is_correct": false
        },
        {
          "is_image": false,
          "is_latex": false,
          "text": "` 1300",
          "latex_string": null,
          "image_url": null,
          "is_correct": false
        },
        {
          "is_image": false,
          "is_latex": false,
          "text": "` 1350",
          "latex_string": null,
          "image_url": null,
          "is_correct": true
        },
        {
          "is_image": false,
          "is_latex": false,
          "text": "` 1500",
          "latex_string": null,
          "image_url": null,
          "is_correct": false
        }
      ]
    },
    {
      "id": "M.7.32.S.12",
      "type": "MCQuestion",
      "text": "A trader owes a merchant ` 10,028 due 1 year hence. The trader wants to settle the account after 3 months. If the rate of interest is 12% per annum, how much cash should he pay?",
      "is_latex": false,
      "is_image": false,
      "image_url": null,
      "latex_string": null,
      "xp": 1,
      "tag": "",
      "difficulty": "EASY",
      "topic": "Financial Mathematics",
      "chapter": "True Discount",
      "option_list": [
        {
          "is_image": false,
          "is_latex": false,
          "text": "` 9025.20",
          "latex_string": null,
          "image_url": null,
          "is_correct": true
        },
        {
          "is_image": false,
          "is_latex": false,
          "text": "` 9200",
          "latex_string": null,
          "image_url": null,
          "is_correct": false
        },
        {
          "is_image": false,
          "is_latex": false,
          "text": "` 9600",
          "latex_string": null,
          "image_url": null,
          "is_correct": false
        },
        {
          "is_image": false,
          "is_latex": false,
          "text": "` 9560",
          "latex_string": null,
          "image_url": null,
          "is_correct": false
        }
      ]
    },
    {
      "id": "M.7.32.S.13",
      "type": "MCQuestion",
      "text": "A man buys a watch for ` 1950 in cash and sells it for ` 2200 at a credit of 1 year. If the rate of interest is 10% per annum, the man",
      "is_latex": false,
      "is_image": false,
      "image_url": null,
      "latex_string": null,
      "xp": 1,
      "tag": "",
      "difficulty": "EASY",
      "topic": "Financial Mathematics",
      "chapter": "True Discount",
      "option_list": [
        {
          "is_image": false,
          "is_latex": false,
          "text": "gains ` 55",
          "latex_string": null,
          "image_url": null,
          "is_correct": false
        },
        {
          "is_image": false,
          "is_latex": false,
          "text": "gains ` 50",
          "latex_string": null,
          "image_url": null,
          "is_correct": true
        },
        {
          "is_image": false,
          "is_latex": false,
          "text": "loses ` 30",
          "latex_string": null,
          "image_url": null,
          "is_correct": false
        },
        {
          "is_image": false,
          "is_latex": false,
          "text": "gains ` 30",
          "latex_string": null,
          "image_url": null,
          "is_correct": false
        }
      ]
    },
    {
      "id": "M.7.32.S.14",
      "type": "MCQuestion",
      "text": "A man purchased a cow for ` 3000 and sold it the same day for ` 3600, allowing the buyer a credit of 2 years. If the rate of interest be 10% per annum, then the man has a gain of",
      "is_latex": false,
      "is_image": false,
      "image_url": null,
      "latex_string": null,
      "xp": 1,
      "tag": "",
      "difficulty": "EASY",
      "topic": "Financial Mathematics",
      "chapter": "True Discount",
      "option_list": [
        {
          "is_image": false,
          "is_latex": false,
          "text": "0%",
          "latex_string": null,
          "image_url": null,
          "is_correct": true
        },
        {
          "is_image": false,
          "is_latex": false,
          "text": "5%",
          "latex_string": null,
          "image_url": null,
          "is_correct": false
        },
        {
          "is_image": false,
          "is_latex": false,
          "text": "7.5%",
          "latex_string": null,
          "image_url": null,
          "is_correct": false
        },
        {
          "is_image": false,
          "is_latex": false,
          "text": "10%",
          "latex_string": null,
          "image_url": null,
          "is_correct": false
        }
      ]
    },
    {
      "id": "M.7.32.S.15",
      "type": "MCQuestion",
      "text": "A owes B, ` 1573 payable 1 1/2 years hence. Also B owes A, ` 1444.50 payable 6 months hence. If they want to settle the account forthwith, keeping 14% as the rate of interest, then who should pay and how much?",
      "is_latex": false,
      "is_image": false,
      "image_url": null,
      "latex_string": null,
      "xp": 1,
      "tag": "M.A.T. 2006; G.B.O., 2007",
      "difficulty": "EASY",
      "topic": "Financial Mathematics",
      "chapter": "True Discount",
      "option_list": [
        {
          "is_image": false,
          "is_latex": false,
          "text": "A, ` 28.50",
          "latex_string": null,
          "image_url": null,
          "is_correct": false
        },
        {
          "is_image": false,
          "is_latex": false,
          "text": "B, ` 37.50",
          "latex_string": null,
          "image_url": null,
          "is_correct": false
        },
        {
          "is_image": false,
          "is_latex": false,
          "text": "A, ` 50",
          "latex_string": null,
          "image_url": null,
          "is_correct": true
        },
        {
          "is_image": false,
          "is_latex": false,
          "text": "B, ` 50",
          "latex_string": null,
          "image_url": null,
          "is_correct": false
        }
      ]
    },
    {
      "id": "M.7.32.S.16",
      "type": "MCQuestion",
      "text": "A has to pay ` 220 to B after 1 year. B asks A to pay ` 110 in cash and defer the payment of ` 110 for 2 years. A agrees to it. If the rate of interest be 10% per annum, in this mode of payment",
      "is_latex": false,
      "is_image": false,
      "image_url": null,
      "latex_string": null,
      "xp": 2,
      "tag": "",
      "difficulty": "MEDIUM",
      "topic": "Financial Mathematics",
      "chapter": "True Discount",
      "option_list": [
        {
          "is_image": false,
          "is_latex": false,
          "text": "There is no gain or loss to anyone",
          "latex_string": null,
          "image_url": null,
          "is_correct": false
        },
        {
          "is_image": false,
          "is_latex": false,
          "text": "A gains ` 7.34",
          "latex_string": null,
          "image_url": null,
          "is_correct": true
        },
        {
          "is_image": false,
          "is_latex": false,
          "text": "A loses ` 7.34",
          "latex_string": null,
          "image_url": null,
          "is_correct": false
        },
        {
          "is_image": false,
          "is_latex": false,
          "text": "A gains ` 11",
          "latex_string": null,
          "image_url": null,
          "is_correct": false
        }
      ]
    },
    {
      "id": "M.7.32.S.17",
      "type": "MCQuestion",
      "text": "` 20 is the true discount on ` 260 due after a certain time. What will be the true discount on the same sum due after half of the former time, the rate of interest being the same?",
      "is_latex": false,
      "is_image": false,
      "image_url": null,
      "latex_string": null,
      "xp": 2,
      "tag": "",
      "difficulty": "MEDIUM",
      "topic": "Financial Mathematics",
      "chapter": "True Discount",
      "option_list": [
        {
          "is_image": false,
          "is_latex": false,
          "text": "` 10",
          "latex_string": null,
          "image_url": null,
          "is_correct": false
        },
        {
          "is_image": false,
          "is_latex": false,
          "text": "` 10.40",
          "latex_string": null,
          "image_url": null,
          "is_correct": true
        },
        {
          "is_image": false,
          "is_latex": false,
          "text": "` 15.20",
          "latex_string": null,
          "image_url": null,
          "is_correct": false
        },
        {
          "is_image": false,
          "is_latex": false,
          "text": "` 13",
          "latex_string": null,
          "image_url": null,
          "is_correct": false
        }
      ]
    },
    {
      "id": "M.7.32.S.18",
      "type": "MCQuestion",
      "text": "The true discount on a certain sum of money due 2 2/3 years hence, is ` 150 and the simple interest on the same sum for the same time and at the same rate is ` 200. Interest rate per annum is",
      "is_latex": false,
      "is_image": false,
      "image_url": null,
      "latex_string": null,
      "xp": 2,
      "tag": "MAT, 2011",
      "difficulty": "MEDIUM",
      "topic": "Financial Mathematics",
      "chapter": "True Discount",
      "option_list": [
        {
          "is_image": false,
          "is_latex": false,
          "text": "10%",
          "latex_string": null,
          "image_url": null,
          "is_correct": false
        },
        {
          "is_image": false,
          "is_latex": false,
          "text": "12%",
          "latex_string": null,
          "image_url": null,
          "is_correct": true
        },
        {
          "is_image": false,
          "is_latex": false,
          "text": "12 1/2%",
          "latex_string": null,
          "image_url": null,
          "is_correct": false
        },
        {
          "is_image": false,
          "is_latex": false,
          "text": "8 1/2%",
          "latex_string": null,
          "image_url": null,
          "is_correct": false
        }
      ]
    },
    {
      "id": "M.7.32.S.19",
      "type": "MCQuestion",
      "text": "` 20 is the true discount on ` 260 due after a certain time. What will be the true discount on the same sum due after half of the former time, the rate of interest being the same?",
      "is_latex": false,
      "is_image": false,
      "image_url": null,
      "latex_string": null,
      "xp": 2,
      "tag": "MAT, 2011",
      "difficulty": "MEDIUM",
      "topic": "Financial Mathematics",
      "chapter": "True Discount",
      "option_list": [
        {
          "is_image": false,
          "is_latex": false,
          "text": "` 15.20",
          "latex_string": null,
          "image_url": null,
          "is_correct": false
        },
        {
          "is_image": false,
          "is_latex": false,
          "text": "` 10.40",
          "latex_string": null,
          "image_url": null,
          "is_correct": true
        },
        {
          "is_image": false,
          "is_latex": false,
          "text": "` 10.83",
          "latex_string": null,
          "image_url": null,
          "is_correct": false
        },
        {
          "is_image": false,
          "is_latex": false,
          "text": "` 13",
          "latex_string": null,
          "image_url": null,
          "is_correct": false
        }
      ]
    },
    {
      "id": "M.7.32.S.20",
      "type": "MCQuestion",
      "text": "The total discount on ` 1860 due after a certain time at 5% is ` 60. Find the time after which it is due",
      "is_latex": false,
      "is_image": false,
      "image_url": null,
      "latex_string": null,
      "xp": 2,
      "tag": "SSC\u2014CHSL (10+2) Exam, 2015",
      "difficulty": "MEDIUM",
      "topic": "Financial Mathematics",
      "chapter": "True Discount",
      "option_list": [
        {
          "is_image": false,
          "is_latex": false,
          "text": "9 months",
          "latex_string": null,
          "image_url": null,
          "is_correct": false
        },
        {
          "is_image": false,
          "is_latex": false,
          "text": "10 months",
          "latex_string": null,
          "image_url": null,
          "is_correct": false
        },
        {
          "is_image": false,
          "is_latex": false,
          "text": "7 months",
          "latex_string": null,
          "image_url": null,
          "is_correct": false
        },
        {
          "is_image": false,
          "is_latex": false,
          "text": "8 months",
          "latex_string": null,
          "image_url": null,
          "is_correct": true
        }
      ]
    },
    {
      "id": "M.7.32.S.21",
      "type": "MCQuestion",
      "text": "The difference between simple interest and the true discount on ` 2400 due 4 years hence at 5% per annum simple interest is",
      "is_latex": false,
      "is_image": false,
      "image_url": null,
      "latex_string": null,
      "xp": 2,
      "tag": "SSC\u2014CHSL (10+2) Exam, 2015",
      "difficulty": "MEDIUM",
      "topic": "Financial Mathematics",
      "chapter": "True Discount",
      "option_list": [
        {
          "is_image": false,
          "is_latex": false,
          "text": "` 70",
          "latex_string": null,
          "image_url": null,
          "is_correct": false
        },
        {
          "is_image": false,
          "is_latex": false,
          "text": "` 30",
          "latex_string": null,
          "image_url": null,
          "is_correct": false
        },
        {
          "is_image": false,
          "is_latex": false,
          "text": "` 50",
          "latex_string": null,
          "image_url": null,
          "is_correct": true
        },
        {
          "is_image": false,
          "is_latex": false,
          "text": "` 80",
          "latex_string": null,
          "image_url": null,
          "is_correct": false
        }
      ]
    }
  ]
}